README.md
setup.cfg
setup.py
dictorm/__init__.py
dictorm/dictorm.py
dictorm/pg.py
dictorm/sqlite.py
dictorm/version.py
dictorm.egg-info/PKG-INFO
dictorm.egg-info/SOURCES.txt
dictorm.egg-info/dependency_links.txt
dictorm.egg-info/requires.txt
dictorm.egg-info/top_level.txt